sublib/__init__.py
sublib/sublib.py
sublib-1.2.1.dist-info/LICENSE
sublib-1.2.1.dist-info/METADATA
sublib-1.2.1.dist-info/WHEEL
sublib-1.2.1.dist-info/top_level.txt
sublib-1.2.1.dist-info/RECORD
