Metadata-Version: 2.1
Name: sublib
Version: 1.2.1
Summary: Python library for easier management and processing of subtitle files.
Home-page: https://github.com/TheFifthLeaf/sublib
Download-URL: https://github.com/TheFifthLeaf/sublib/archive/refs/tags/v1.2.1.zip
Author: Dawid Jach
Author-email: jach.developer@protonmail.com
License: GNU GPLv3
Project-URL: pypi, https://pypi.org/project/sublib/
Keywords: python,subtitle,subtitles,subrip,microdvd,mplayer,mplayer2,tmplayer,movies,mkv,converter,sublib
Classifier: Development Status :: 3 - Alpha
Classifier: Intended Audience :: Developers
Classifier: Topic :: Software Development :: Build Tools
Classifier: License :: OSI Approved :: GNU General Public License v3 (GPLv3)
Classifier: Natural Language :: English
Classifier: Programming Language :: Python :: 3.6
Classifier: Programming Language :: Python :: 3.7
Classifier: Programming Language :: Python :: 3.8
Classifier: Programming Language :: Python :: 3.9
Classifier: Programming Language :: Python :: 3.10
Classifier: Operating System :: POSIX :: Linux
Classifier: Operating System :: MacOS :: MacOS X
Classifier: Operating System :: Microsoft :: Windows
Requires-Python: >=3.6
License-File: LICENSE
